__init__.py
main.py
pydantic_settings_create-0.1.0.dist-info/METADATA
pydantic_settings_create-0.1.0.dist-info/WHEEL
pydantic_settings_create-0.1.0.dist-info/top_level.txt
pydantic_settings_create-0.1.0.dist-info/RECORD
